protoletariat/__init__.py
protoletariat/__main__.py
protoletariat/fdsetgen.py
protoletariat/rewrite.py
protoletariat/tests/__init__.py
protoletariat/tests/conftest.py
protoletariat/tests/test_fix_imports.py
protoletariat/tests/test_rewrite.py
protoletariat-3.3.10.dist-info/LICENSE
protoletariat-3.3.10.dist-info/METADATA
protoletariat-3.3.10.dist-info/WHEEL
protoletariat-3.3.10.dist-info/entry_points.txt
protoletariat-3.3.10.dist-info/RECORD
