Metadata-Version: 2.1
Name: protoletariat
Version: 3.3.10
Summary: Python protocol buffers for the rest of us
Home-page: https://github.com/cpcloud/protoletariat
License: Apache-2.0
Author: Phillip Cloud
Author-email: 417981+cpcloud@users.noreply.github.com
Maintainer: Phillip Cloud
Maintainer-email: 417981+cpcloud@users.noreply.github.com
Requires-Python: >=3.8,<4.0
Classifier: License :: OSI Approved :: Apache Software License
Classifier: Operating System :: OS Independent
Classifier: Programming Language :: Python
Classifier: Programming Language :: Python :: 3
Classifier: Programming Language :: Python :: 3.8
Classifier: Programming Language :: Python :: 3.9
Classifier: Programming Language :: Python :: 3.10
Classifier: Programming Language :: Python :: 3.11
Classifier: Programming Language :: Python :: 3.12
Classifier: Programming Language :: Python :: 3.13
Provides-Extra: grpcio-tools
Requires-Dist: astunparse (>=1.6.3,<2) ; python_version < "3.9"
Requires-Dist: click (>=8,<9)
Requires-Dist: grpcio-tools (>=1.42.0,<2) ; extra == "grpcio-tools"
Requires-Dist: protobuf (>=3.19.1,<6)
Project-URL: Repository, https://github.com/cpcloud/protoletariat
